[
  {
    "platform": "substack",
    "sourceId": "lenny.substack.com",
    "sourceName": "Lenny's Newsletter",
    "sourceUrl": "https://lenny.substack.com",
    "authorName": "Lenny Rachitsky",
    "authorBio": null,
    "authorAvatarUrl": null,
    "publicEmail": null,
    "hasEmail": false,
    "twitter": null,
    "linkedin": null,
    "website": null,
    "socialLinks": "",
    "audienceSize": null,
    "relevanceScore": 1,
    "audienceScore": 0,
    "qualified": true,
    "contactReady": false
  },
  {
    "platform": "substack",
    "sourceId": "lenny.substack.com",
    "sourceName": "Lenny's Newsletter",
    "sourceUrl": "https://lenny.substack.com",
    "authorName": "Claire Vo",
    "authorBio": null,
    "authorAvatarUrl": null,
    "publicEmail": null,
    "hasEmail": false,
    "twitter": null,
    "linkedin": null,
    "website": null,
    "socialLinks": "",
    "audienceSize": null,
    "relevanceScore": 1,
    "audienceScore": 0,
    "qualified": true,
    "contactReady": false
  }
]
